sageball/__init__.py
sageball-1.0.4.dist-info/LICENSE
sageball-1.0.4.dist-info/METADATA
sageball-1.0.4.dist-info/WHEEL
sageball-1.0.4.dist-info/top_level.txt
sageball-1.0.4.dist-info/RECORD
